{"index":"./index.html","header":[{"name":"Tutoriales","url":"./documentation/_config.yaml","data":[{"name":"Introducción","url":"introduction.html"},{"name":"Comenzar a usar","content":[{"name":"Referencia de scripts","url":"script-reference.html"},{"name":"Crear la primera aplicación","url":"create-first-app.html"}]},{"name":"Inicio rápido","url":"quick-start.html"},{"name":"Sintaxis de plantillas","content":[{"name":"Renderizado de contenido","url":"content-rendering.html"},{"name":"Enlace de eventos","url":"event-binding.html"},{"name":"Respuesta de propiedades","url":"property-response.html"},{"name":"Enlace de propiedades","url":"property-binding.html"},{"name":"Enlace de clases y estilos","url":"class-style-binding.html"},{"name":"Renderizado condicional","url":"conditional-rendering.html"},{"name":"Renderizado de listas","url":"list-rendering.html"},{"name":"Propiedades computadas","url":"computed-properties.html"},{"name":"Observadores","url":"watchers.html"},{"name":"Ciclo de vida","url":"lifecycle.html"}]},{"name":"Componentes","content":[{"name":"Crear componente","url":"create-component.html"},{"name":"Pasar atributos característicos","url":"inherit-attributes.html"},{"name":"Slots","url":"slots.html"},{"name":"Comprender el enlace de propiedades profundo","url":"deep-property-binding.html"},{"name":"Eventos personalizados","url":"custom-events.html"}]},{"name":"Aplicación y escalado","content":[{"name":"Micro-aplicación","url":"micro-app.html"},{"name":"Configuración de aplicación y funciones relacionadas","url":"app-configuration.html"},{"name":"Aplicación de página única","url":"routes.html"},{"name":"Páginas/rutas anidadas","url":"nested-routes.html"},{"name":"SSR","url":"ssr.html"}]},{"name":"Gestión de estado","content":[{"name":"Qué es la gestión de estado","url":"state-management.html"},{"name":"Estado de contexto","url":"context-state.html"},{"name":"Consulta de estilos","url":"match-var.html"}]},{"name":"Producción y despliegue","url":"build-app.html"},{"name":"Otros componentes","content":[{"name":"Inyectar estilos del host","url":"inject-host-style.html"},{"name":"Componente no explícito","url":"non-explicit-component.html"},{"name":"Componente replace-temp","url":"replace-template.html"}]}],"firstUrl":"documentation/introduction.html","prefix":"documentation/"},{"name":"API","url":"./api/_config.yaml","data":[{"name":"Referencia de API","url":"api.html"},{"name":"Relacionado con instancias","content":[{"name":"$(selector)","url":"instance/dollar.html"},{"name":"all","url":"instance/all.html"},{"name":"shadow","url":"instance/shadow.html"},{"name":"prev","url":"instance/prev.html"},{"name":"prevs","url":"instance/prevs.html"},{"name":"next","url":"instance/next.html"},{"name":"nexts","url":"instance/nexts.html"},{"name":"siblings","url":"instance/siblings.html"},{"name":"parent","url":"instance/parent.html"},{"name":"parents","url":"instance/parents.html"},{"name":"clone","url":"instance/clone.html"},{"name":"ele","url":"instance/ele.html"},{"name":"root","url":"instance/root.html"},{"name":"Elementos hijos","url":"instance/children.html"},{"name":"host","url":"instance/host.html"},{"name":"app","url":"instance/app.html"}]},{"name":"Operaciones de nodos","content":[{"name":"Agregar o eliminar elementos hijos","url":"operation/array-like.html"},{"name":"before","url":"operation/before.html"},{"name":"after","url":"operation/after.html"},{"name":"remove","url":"operation/remove.html"},{"name":"wrap","url":"operation/wrap.html"},{"name":"unwrap","url":"operation/unwrap.html"}]},{"name":"Operaciones de atributos","content":[{"name":"text","url":"props/text.html"},{"name":"html","url":"props/html.html"},{"name":"attr","url":"props/attr.html"},{"name":"css","url":"props/css.html"},{"name":"style","url":"props/style.html"},{"name":"classList","url":"props/class-list.html"},{"name":"data","url":"props/data.html"}]},{"name":"Relacionado con eventos","content":[{"name":"on","url":"event/on.html"},{"name":"one","url":"event/one.html"},{"name":"emit","url":"event/emit.html"},{"name":"off","url":"event/off.html"}]},{"name":"Otros","content":[{"name":"Componente o-app","url":"others/app.html"},{"name":"Componente o-page","url":"others/page.html"},{"name":"formData","url":"others/form-data.html"},{"name":"tag","url":"others/tag.html"},{"name":"index","url":"others/index.html"},{"name":"is","url":"others/is.html"},{"name":"refresh","url":"others/refresh.html"},{"name":"PATH","url":"others/path.html"},{"name":"extend","url":"others/extend.html"},{"name":"version","url":"others/version.html"},{"name":"Características de datos de instancia","url":"others/stanz.html"}]}],"firstUrl":"api/api.html","prefix":"api/"},{"name":"Otros","content":[{"name":"Preguntas y respuestas de escenarios","url":"./scenarios/_config.yaml","data":[{"name":"Ventajas de ofa.js para el uso de IA","url":"more-suitable-for-ai.html"}],"firstUrl":"scenarios/more-suitable-for-ai.html","prefix":"scenarios/"}]}],"languages":["cn","en","ja","ko","es"]}